LICENSE
MANIFEST.in
README.md
VERSION
requirements.txt
setup.cfg
setup.py
powerful_pipes_notifier/__init__.py
powerful_pipes_notifier/__main__.py
powerful_pipes_notifier/config.py
powerful_pipes_notifier/exceptions.py
powerful_pipes_notifier/rules_engine.py
powerful_pipes_notifier.egg-info/PKG-INFO
powerful_pipes_notifier.egg-info/SOURCES.txt
powerful_pipes_notifier.egg-info/dependency_links.txt
powerful_pipes_notifier.egg-info/entry_points.txt
powerful_pipes_notifier.egg-info/requires.txt
powerful_pipes_notifier.egg-info/top_level.txt
powerful_pipes_notifier.egg-info/zip-safe
powerful_pipes_notifier/destinations/__init__.py
powerful_pipes_notifier/destinations/connect.py
powerful_pipes_notifier/destinations/interface.py
powerful_pipes_notifier/destinations/mongodb.py
powerful_pipes_notifier/destinations/webhook.py